{
  "-2,0": {
    "SourceVersionHash": "i7etjL8U20qhYXfkn/3QhApi5dI=",
    "VersionHash": "XP5NpXPqpGOCCqsqI5ROmP+MfGU="
  },
  "-1,0": {
    "SourceVersionHash": "gbFvOBNigRhzGFpXVhStPBXqcvY=",
    "VersionHash": "XP5NpXPqpGOCCqsqI5ROmP+MfGU="
  },
  "-3,1": {
    "SourceVersionHash": "J0rAOCZsqQy9xnBVuKzq0+rmnio=",
    "VersionHash": "XP5NpXPqpGOCCqsqI5ROmP+MfGU="
  },
  "-2,1": {
    "SourceVersionHash": "p8bZoZMd1bFxdEHCTB/O4cTPJGQ=",
    "VersionHash": "XP5NpXPqpGOCCqsqI5ROmP+MfGU="
  },
  "-1,1": {
    "SourceVersionHash": "b7HbBoCb/ecODau+lH2KBjKaKPQ=",
    "VersionHash": "XP5NpXPqpGOCCqsqI5ROmP+MfGU="
  },
  "-3,2": {
    "SourceVersionHash": "J0rAOCZsqQy9xnBVuKzq0+rmnio=",
    "VersionHash": "XP5NpXPqpGOCCqsqI5ROmP+MfGU="
  },
  "-2,2": {
    "SourceVersionHash": "P3wI020wrFeZESQmJ/8eCgDjC/Q=",
    "VersionHash": "XP5NpXPqpGOCCqsqI5ROmP+MfGU="
  },
  "-1,2": {
    "SourceVersionHash": "rt8FgUJ7p3gDlEm+RvklbIzAGm8=",
    "VersionHash": "XP5NpXPqpGOCCqsqI5ROmP+MfGU="
  }
}